yunhu2onebot12/__init__.py
yunhu2onebot12/convert.py
yunhu2onebot12-1.1.2.dist-info/METADATA
yunhu2onebot12-1.1.2.dist-info/WHEEL
yunhu2onebot12-1.1.2.dist-info/top_level.txt
yunhu2onebot12-1.1.2.dist-info/RECORD
