Metadata-Version: 2.4
Name: yunhu2onebot12
Version: 1.1.2
Summary: 云湖事件到OneBot12的协议格式转换器
Author-email: wsu2059q <wsu2059@qq.com>
License: MIT
Project-URL: Homepage, https://github.com/wsu2059q/YunhuAdapter4OneBot12
Project-URL: Repository, https://github.com/wsu2059q/YunhuAdapter4OneBot12
Project-URL: Issues, https://github.com/wsu2059q/YunhuAdapter4OneBot12/issues
Classifier: Programming Language :: Python :: 3
Classifier: License :: OSI Approved :: MIT License
Classifier: Operating System :: OS Independent
Requires-Python: >=3.7
